cheby.cpython-311-darwin.so
cheby-0.3.8.dist-info/RECORD
cheby-0.3.8.dist-info/LICENSE
cheby-0.3.8.dist-info/WHEEL
cheby-0.3.8.dist-info/top_level.txt
cheby-0.3.8.dist-info/METADATA
