Metadata-Version: 2.1
Name: cheby
Version: 0.3.8
Summary: Functions represented as Chebyshev series
Home-page: https://github.com/GwenaelGabard/cheby
Author: Gwénaël Gabard
Author-email: gwenael.gabard@univ-lemans.fr
Requires-Python: >=3.7
License-File: LICENSE
Provides-Extra: test
Requires-Dist: pytest>=6.0; extra == "test"
